db_transfer/__init__.py
db_transfer/adapter.py
db_transfer/adapter_file.py
db_transfer/adapter_redis.py
db_transfer/adapter_yaml.py
db_transfer/cli.py
db_transfer/transfer.py
DB_Transfer-0.5.6.dist-info/LICENSE
DB_Transfer-0.5.6.dist-info/METADATA
DB_Transfer-0.5.6.dist-info/WHEEL
DB_Transfer-0.5.6.dist-info/entry_points.txt
DB_Transfer-0.5.6.dist-info/top_level.txt
DB_Transfer-0.5.6.dist-info/RECORD
