Metadata-Version: 2.1
Name: DB-Transfer
Version: 0.5.6
Summary: An easy way to fetch and store data from and store to key-value databases like Redis.
Home-page: https://github.com/arrrlo/db-transfer
Author: Ivan Arar
Author-email: ivan.arar@gmail.com
License: MIT
Project-URL: Source, https://github.com/arrrlo/db-transfer
Keywords: database,redis,transfer,migration
Platform: UNKNOWN
Classifier: Development Status :: 4 - Beta
Classifier: Intended Audience :: Developers
Classifier: Topic :: Software Development :: Build Tools
Classifier: License :: OSI Approved :: MIT License
Classifier: Programming Language :: Python :: 2.7
Classifier: Programming Language :: Python :: 3.7
Requires-Dist: click (>=6.3)
Requires-Dist: redis (>=2.10)
Requires-Dist: ujson (>=1.35)
Requires-Dist: six (>=1.12.0)
Requires-Dist: PyYAML (>=5.1.2)
